seeder/__init__.py
seeder/_modidx.py
seeder/core.py
seeder-0.0.5.dist-info/LICENSE
seeder-0.0.5.dist-info/METADATA
seeder-0.0.5.dist-info/WHEEL
seeder-0.0.5.dist-info/entry_points.txt
seeder-0.0.5.dist-info/top_level.txt
seeder-0.0.5.dist-info/RECORD
