Metadata-Version: 2.1
Name: seeder
Version: 0.0.5
Summary: util torch
Home-page: https://github.com/dsm-72/seeder
Author: dsm-72
Author-email: sumner.magruder@yale.edu
License: Apache Software License 2.0
Keywords: utility for seeding
Classifier: Development Status :: 4 - Beta
Classifier: Intended Audience :: Developers
Classifier: Natural Language :: English
Classifier: Programming Language :: Python :: 3.11
Classifier: License :: OSI Approved :: Apache Software License
Requires-Python: >=3.11
License-File: LICENSE
Requires-Dist: lull
Provides-Extra: dev
Requires-Dist: numpy ; extra == 'dev'
Requires-Dist: pandas ; extra == 'dev'
Requires-Dist: matplotlib ; extra == 'dev'
Requires-Dist: torch ; extra == 'dev'
Requires-Dist: pytorch-lightning ; extra == 'dev'
Requires-Dist: torchvision ; extra == 'dev'
